{
  "sessions": [
    {
      "session": 1,
      "values": {
        "Shimazu Shura": 1,
        "Fawkes Keel": 1,
        "Battista Vivaldi": 1,
        "Gulliver Glaurt": 1,
        "Shivbh": 1,
        "Gouran Marie": 1,
        "Yosuke Mi'sen": 1,
        "Scudamoore Lionel": 1,
        "Musashi Yato": 1,
        "Shreya Yona": 1,
        "Celestia Orion": 1,
        "Lowe Tambora": 1,
        "Timworth": 1,
        "Pentago Quintessa": 1
      }
    },
    {
      "session": 2,
      "values": {
        "Shimazu Shura": 1,
        "Fawkes Keel": 1,
        "Battista Vivaldi": 1,
        "Gulliver Glaurt": 1,
        "Shivbh": 1,
        "Gouran Marie": 1,
        "Yosuke Mi'sen": 1,
        "Scudamoore Lionel": 1,
        "Musashi Yato": 1,
        "Shreya Yona": 1,
        "Celestia Orion": 1,
        "Lowe Tambora": 1,
        "Timworth": 1,
        "Pentago Quintessa": 1
      }
    },
    {
      "session": 3,
      "values": {
        "Shimazu Shura": 1,
        "Fawkes Keel": 1,
        "Battista Vivaldi": 1,
        "Gulliver Glaurt": 1,
        "Shivbh": 1,
        "Gouran Marie": 1,
        "Yosuke Mi'sen": 1,
        "Scudamoore Lionel": 1,
        "Musashi Yato": 1,
        "Shreya Yona": 1,
        "Celestia Orion": 1,
        "Lowe Tambora": 1,
        "Timworth": 1,
        "Pentago Quintessa": 1
      }
    },
    {
      "session": 4,
      "values": {
        "Shimazu Shura": 1,
        "Fawkes Keel": 1,
        "Battista Vivaldi": 1,
        "Gulliver Glaurt": 1,
        "Shivbh": 1,
        "Gouran Marie": 1,
        "Yosuke Mi'sen": 1,
        "Scudamoore Lionel": 1,
        "Musashi Yato": 1,
        "Shreya Yona": 1,
        "Celestia Orion": 1,
        "Lowe Tambora": 1,
        "Timworth": 1,
        "Pentago Quintessa": 1
      }
    },
    {
      "session": 5,
      "values": {
        "Shimazu Shura": 1,
        "Fawkes Keel": 1,
        "Battista Vivaldi": 1,
        "Gulliver Glaurt": 1,
        "Shivbh": 1,
        "Gouran Marie": 1,
        "Yosuke Mi'sen": 1,
        "Scudamoore Lionel": 1,
        "Musashi Yato": 1,
        "Shreya Yona": 1,
        "Celestia Orion": 1,
        "Lowe Tambora": 1,
        "Timworth": 1,
        "Pentago Quintessa": 1
      }
    },
    {
      "session": 6,
      "values": {
        "Shimazu Shura": 1,
        "Fawkes Keel": 1,
        "Battista Vivaldi": 1,
        "Gulliver Glaurt": 1,
        "Shivbh": 1,
        "Gouran Marie": 1,
        "Yosuke Mi'sen": 1,
        "Scudamoore Lionel": 1,
        "Musashi Yato": 1,
        "Shreya Yona": 1,
        "Celestia Orion": 1,
        "Lowe Tambora": 1,
        "Timworth": 1,
        "Pentago Quintessa": 1
      }
    },
    {
      "session": 7,
      "values": {
        "Shimazu Shura": 1,
        "Fawkes Keel": 1,
        "Battista Vivaldi": 1,
        "Gulliver Glaurt": 1,
        "Shivbh": 1,
        "Gouran Marie": 1,
        "Yosuke Mi'sen": 1,
        "Scudamoore Lionel": 1,
        "Musashi Yato": 1,
        "Shreya Yona": 1,
        "Celestia Orion": 1,
        "Lowe Tambora": 1,
        "Timworth": 1,
        "Pentago Quintessa": 1
      }
    },
    {
      "session": 8,
      "values": {
        "Shimazu Shura": 1,
        "Fawkes Keel": 1,
        "Battista Vivaldi": 1,
        "Gulliver Glaurt": 1,
        "Shivbh": 1,
        "Gouran Marie": 1,
        "Yosuke Mi'sen": 1,
        "Scudamoore Lionel": 1,
        "Musashi Yato": 1,
        "Shreya Yona": 1,
        "Celestia Orion": 1,
        "Lowe Tambora": 1,
        "Timworth": 1,
        "Pentago Quintessa": 1
      }
    },
    {
      "session": 9,
      "values": {
        "Shimazu Shura": 1,
        "Fawkes Keel": 1,
        "Battista Vivaldi": 1,
        "Gulliver Glaurt": 1,
        "Shivbh": 1,
        "Gouran Marie": 1,
        "Yosuke Mi'sen": 1,
        "Scudamoore Lionel": 1,
        "Musashi Yato": 1,
        "Shreya Yona": 1,
        "Celestia Orion": 0.5,
        "Lowe Tambora": 1,
        "Timworth": 1,
        "Pentago Quintessa": 1
      }
    }
  ]
}